freegs/README.md
freegs/__init__.py
freegs/_divgeo.py
freegs/_version.py
freegs/boundary.py
freegs/coil.py
freegs/control.py
freegs/critical.py
freegs/divgeo.py
freegs/dump.py
freegs/equilibrium.py
freegs/fieldtracer.py
freegs/filament_coil.py
freegs/geqdsk.py
freegs/gradshafranov.py
freegs/jtor.py
freegs/machine.py
freegs/multi_coil.py
freegs/multigrid.py
freegs/optimise.py
freegs/optimiser.py
freegs/picard.py
freegs/plotting.py
freegs/polygons.py
freegs/pre_calc_coil.py
freegs/quadrature.py
freegs/shaped_coil.py
freegs/test_critical.py
freegs/test_equilibrium.py
freegs/test_filament_coil.py
freegs/test_jtor.py
freegs/test_linearsolve.py
freegs/test_machine.py
freegs/test_optimise.py
freegs/test_optimiser.py
freegs/test_polygons.py
freegs/test_quadrature.py
freegs/test_readwrite.py
freegs/test_sensors.py
freegs/test_shaped_coil.py
FreeGS-0.8.2.dist-info/LICENSE
FreeGS-0.8.2.dist-info/METADATA
FreeGS-0.8.2.dist-info/WHEEL
FreeGS-0.8.2.dist-info/top_level.txt
FreeGS-0.8.2.dist-info/RECORD
