Metadata-Version: 2.1
Name: FreeGS
Version: 0.8.2
Summary: Free boundary Grad-Shafranov solver for tokamak plasma equilibria
Author-email: Ben Dudson <benjamin.dudson@york.ac.uk>
License: GNU Lesser General Public License v3 or later (LGPLv3+)
Project-URL: project, https://github.com/freegs-plasma/freegs
Classifier: Programming Language :: Python
Classifier: Development Status :: 3 - Alpha
Classifier: Natural Language :: English
Classifier: Intended Audience :: Science/Research
Classifier: License :: OSI Approved :: GNU Lesser General Public License v3 or later (LGPLv3+)
Classifier: Operating System :: OS Independent
Classifier: Programming Language :: Python
Classifier: Topic :: Software Development :: Libraries :: Python Modules
Classifier: Topic :: Scientific/Engineering :: Physics
Requires-Python: >=3.8
License-File: LICENSE
Requires-Dist: numpy >=1.8
Requires-Dist: scipy >=0.14
Requires-Dist: matplotlib >=1.3
Requires-Dist: h5py >=2.10.0
Requires-Dist: Shapely >=1.7.1
Requires-Dist: freeqdsk >=0.1.0
Provides-Extra: docs
Requires-Dist: sphinx >=5.3 ; extra == 'docs'
Requires-Dist: sphinx-autodoc-typehints >=1.19 ; extra == 'docs'
Requires-Dist: sphinx-book-theme >=0.4.0rc1 ; extra == 'docs'
Provides-Extra: tests
Requires-Dist: pytest ; extra == 'tests'
